algo_trade/__init__.py
algo_trade/account.py
algo_trade/backtest.py
algo_trade/data.py
algo_trade/event.py
algo_trade/execution.py
algo_trade/portfolio.py
algo_trade/strategy.py
algo_trade/utilities.py
algo_trade-0.2.13.dist-info/LICENSE
algo_trade-0.2.13.dist-info/METADATA
algo_trade-0.2.13.dist-info/WHEEL
algo_trade-0.2.13.dist-info/top_level.txt
algo_trade-0.2.13.dist-info/RECORD
