Metadata-Version: 2.1
Name: algo-trade
Version: 0.2.13
Summary: Small package to test and implement portfolio trading algorithms
Home-page: https://github.com/vtamprateep/algo-trade
Author: Vinyou Tamprateep
License: UNKNOWN
Platform: UNKNOWN
Classifier: Programming Language :: Python :: 3
Classifier: License :: OSI Approved :: MIT License
Classifier: Operating System :: OS Independent
Requires-Python: >=3.6
Requires-Dist: tda-api
Requires-Dist: pandas
Requires-Dist: numpy
Requires-Dist: yfinance
